superopenai/__init__.py
superopenai/cache.py
superopenai/estimator.py
superopenai/state.py
superopenai/types.py
superopenai/wrap_openai.py
superopenai-0.1.2.dist-info/METADATA
superopenai-0.1.2.dist-info/WHEEL
superopenai-0.1.2.dist-info/RECORD
