Metadata-Version: 2.1
Name: superopenai
Version: 0.1.2
Summary: Logging and caching superpowers for the openai sdk
Home-page: https://github.com/villagecomputing/superopenai
License: MIT
Author: Aman Dhesi
Author-email: aman@stelolabs.com
Requires-Python: >=3.10,<4.0
Classifier: License :: OSI Approved :: MIT License
Classifier: Programming Language :: Python :: 3
Classifier: Programming Language :: Python :: 3.10
Classifier: Programming Language :: Python :: 3.11
Requires-Dist: cachetools (>=5.3.2,<6.0.0)
Requires-Dist: contextvars (>=2.4,<3.0)
Requires-Dist: openai (>=1.12.0,<2.0.0)
Requires-Dist: prettytable (>=3.10.0,<4.0.0)
Requires-Dist: tiktoken (>=0.6.0,<0.7.0)
Project-URL: Repository, https://github.com/villagecomputing/superopenai
